potodds/__init__.py
potodds/core.py
potodds/main.py
potodds/test_core.py
dante_pot_odds-0.1.dist-info/LICENSE
dante_pot_odds-0.1.dist-info/METADATA
dante_pot_odds-0.1.dist-info/WHEEL
dante_pot_odds-0.1.dist-info/entry_points.txt
dante_pot_odds-0.1.dist-info/top_level.txt
dante_pot_odds-0.1.dist-info/RECORD
